mdx_gh_links.py
mdx_gh_links-0.4.dist-info/LICENSE
mdx_gh_links-0.4.dist-info/METADATA
mdx_gh_links-0.4.dist-info/WHEEL
mdx_gh_links-0.4.dist-info/top_level.txt
mdx_gh_links-0.4.dist-info/RECORD
