Metadata-Version: 2.1
Name: mdx-gh-links
Version: 0.4
Summary: An extension to Python-Markdown which adds support for shorthand links to GitHub users, repositories, issues and commits.
Author-email: Waylan limberg <waylan.limberg@icloud.com>
License: Python-Markdown Github-Links Extension is Copyright (c) 2017-2018 by Waylan
Project-URL: Homepage, https://pypi.org/project/mdx-gh-links/
Project-URL: Repository, https://github.com/Python-Markdown/github-links
Project-URL: Issue Tracker, https://github.com/Python-Markdown/github-links/issues
Keywords: markdown,python-markdown,github
Classifier: Development Status :: 4 - Beta
Classifier: License :: OSI Approved :: BSD License
Classifier: Operating System :: OS Independent
Classifier: Programming Language :: Python
Classifier: Programming Language :: Python :: 3
Classifier: Programming Language :: Python :: 3.8
Classifier: Programming Language :: Python :: 3.9
Classifier: Programming Language :: Python :: 3.10
Classifier: Programming Language :: Python :: 3.11
Classifier: Programming Language :: Python :: Implementation :: CPython
Classifier: Programming Language :: Python :: Implementation :: PyPy
Classifier: Topic :: Documentation
Classifier: Topic :: Text Processing
Classifier: Topic :: Text Processing :: Markup
Classifier: Topic :: Text Processing :: Markup :: HTML
License-File: LICENSE
Requires-Dist: markdown>=3.0.0
